README.rst
setup.py
score.dbgsrv.egg-info/PKG-INFO
score.dbgsrv.egg-info/SOURCES.txt
score.dbgsrv.egg-info/dependency_links.txt
score.dbgsrv.egg-info/namespace_packages.txt
score.dbgsrv.egg-info/not-zip-safe
score.dbgsrv.egg-info/requires.txt
score.dbgsrv.egg-info/top_level.txt
score/dbgsrv/__init__.py
score/dbgsrv/_changedetect.py
score/dbgsrv/_runner.py
score/dbgsrv/_server.py