Metadata-Version: 1.1
Name: score.dbgsrv
Version: 0.1
Summary: Debugging server of The SCORE Framework
Home-page: http://score-framework.org
Author: strg.at
Author-email: score@strg.at
License: LGPL
Keywords: score framework server debug
Platform: UNKNOWN
Classifier: Development Status :: 3 - Alpha
Classifier: Environment :: Console
Classifier: Environment :: Web Environment
Classifier: Framework :: Pyramid
Classifier: Intended Audience :: Developers
Classifier: License :: OSI Approved :: GNU Lesser General Public License v3 or later (LGPLv3+)
Classifier: Operating System :: OS Independent
Classifier: Programming Language :: Python :: 3
Classifier: Programming Language :: Python :: 3.4
Classifier: Programming Language :: Python :: 3.5
Classifier: Topic :: Software Development :: Libraries :: Application Frameworks
